pytelnetMK
