Metadata-Version: 1.2
Name: pytelnetMK
Version: 0.0.4
Summary: Connect Mikrotik telnet server using Telnetlib 
Home-page: http://www.preciseipostei.com.br
Author: pklarner
Author-email: pedro@preciseipostei.com.br
License: UNKNOWN
Platform: UNKNOWN
Requires-Python: >=3
